ck8s/__init__.py
ck8s/action.py
ck8s/cli.py
ck8s/helpers.py
ck8s/testAction.py
ck8s-0.0.2.dist-info/METADATA
ck8s-0.0.2.dist-info/WHEEL
ck8s-0.0.2.dist-info/entry_points.txt
ck8s-0.0.2.dist-info/top_level.txt
ck8s-0.0.2.dist-info/RECORD
