Metadata-Version: 2.1
Name: ck8s
Version: 0.0.2
Summary: CK8S POC command line
Author: Ayoub ED-DAFALI
Author-email: ayoub.eddafali@elastisys.com
Requires-Dist: kubernetes
